othello_parser/__init__.py
othello_parser/lab1.py
othello_parser/lab2.py
othello_parser/lab3.py
othello_parser/lab4.py
othello_parser/lab5.py
othello_parser/lab6.py
othello_parser/lab7.py
othello_parser/lab8.py
othello_parser-1.2.1.dist-info/DESCRIPTION.rst
othello_parser-1.2.1.dist-info/METADATA
othello_parser-1.2.1.dist-info/RECORD
othello_parser-1.2.1.dist-info/WHEEL
othello_parser-1.2.1.dist-info/metadata.json
othello_parser-1.2.1.dist-info/top_level.txt
