Metadata-Version: 2.0
Name: othello-parser
Version: 1.2.1
Summary: Othello Parser for TJHSST Labs
Home-page: https://github.com/ovkulkarni/othello-parser
Author: Omkar Kulkarni
Author-email: okulkarni@tjhsst.edu
License: UNKNOWN
Download-URL: https://github.com/ovkulkarni/othello-parser/archive/1.2.1.tar.gz
Keywords: othello,argparse,tjhsst,gabor,parser
Platform: UNKNOWN
